k4a_module.cp314-win_amd64.pyd
pyk4a/__init__.py
pyk4a/calibration.py
pyk4a/capture.py
pyk4a/config.py
pyk4a/depthengine_2_0.dll
pyk4a/errors.py
pyk4a/k4a.dll
pyk4a/k4arecord.dll
pyk4a/module.py
pyk4a/playback.py
pyk4a/py.typed
pyk4a/pyk4a.cpp
pyk4a/pyk4a.py
pyk4a/record.py
pyk4a/results.py
pyk4a/transformation.py
pyk4a/win32_utils.py
pyk4a_bundle-1.5.0.1.dist-info/licenses/LICENSE
pyk4a_bundle-1.5.0.1.dist-info/METADATA
pyk4a_bundle-1.5.0.1.dist-info/WHEEL
pyk4a_bundle-1.5.0.1.dist-info/top_level.txt
pyk4a_bundle-1.5.0.1.dist-info/RECORD
