Metadata-Version: 2.4
Name: pyk4a-bundle
Version: 1.5.0.1
Summary: Python wrapper over Azure Kinect SDK
Home-page: https://github.com/cansik/pyk4a/
License: MIT
Classifier: Operating System :: OS Independent
Classifier: Development Status :: 4 - Beta
Classifier: Topic :: Multimedia :: Video :: Capture
Classifier: Programming Language :: Python :: 3
Classifier: Programming Language :: C
Requires-Python: >=3.4
License-File: LICENSE
Requires-Dist: numpy
Dynamic: license-file
